pyracetimegg/__init__.py
pyracetimegg/api.py
pyracetimegg/category.py
pyracetimegg/object_mapping.py
pyracetimegg/race.py
pyracetimegg/test_api.py
pyracetimegg/throttled_request.py
pyracetimegg/user.py
pyracetimegg/utils.py
pyracetimegg/objects/__init__.py
pyracetimegg/objects/category.py
pyracetimegg/objects/race.py
pyracetimegg/objects/user.py
pyracetimegg-2.3.0.dist-info/LICENSE
pyracetimegg-2.3.0.dist-info/METADATA
pyracetimegg-2.3.0.dist-info/WHEEL
pyracetimegg-2.3.0.dist-info/top_level.txt
pyracetimegg-2.3.0.dist-info/RECORD
